pylorentz
