Metadata-Version: 1.1
Name: pylorentz
Version: 0.1.0
Summary: Python project to work with 4-vectors and Lorentz boots in high energy physics.
Home-page: https://gitlab.sauerburger.com/frank/pylorentz
Author: Frank Sauerburger
Author-email: frank@sauerburger.com
License: MIT
Platform: UNKNOWN
Classifier: Intended Audience :: Science/Research
Classifier: License :: OSI Approved :: MIT License
Classifier: Operating System :: OS Independent
Classifier: Programming Language :: Python :: 3.5
Classifier: Programming Language :: Python :: 3.6
Classifier: Programming Language :: Python :: 3.7
Classifier: Topic :: Scientific/Engineering :: Physics
